coupons/__init__.py
coupons/filters.py
coupons/models.py
coupons/serializers.py
coupons/urls.py
coupons/views.py
coupons/migrations/0001_initial.py
coupons/migrations/__init__.py
coupons/tests/__init__.py
coupons/tests/base.py
coupons/tests/test_coupon_create.py
coupons/tests/test_coupon_create_group.py
coupons/tests/test_coupon_delete.py
coupons/tests/test_coupon_delete_group.py
coupons/tests/test_coupon_list.py
coupons/tests/test_coupon_list_filter.py
coupons/tests/test_coupon_list_group.py
coupons/tests/test_coupon_list_search.py
coupons/tests/test_coupon_redeem.py
coupons/tests/test_coupon_redeemed.py
coupons/tests/test_coupon_redeemed_group.py
coupons/tests/test_coupon_retrieve.py
coupons/tests/test_coupon_update.py
coupons/tests/test_coupon_update_group.py
coupons/tests/test_redeemed_delete.py
coupons/tests/test_redeemed_delete_group.py
coupons/tests/test_redeemed_list.py
coupons/tests/test_redeemed_list_filter.py
coupons/tests/test_redeemed_list_group.py
drf_coupons-1.0.dist-info/DESCRIPTION.rst
drf_coupons-1.0.dist-info/METADATA
drf_coupons-1.0.dist-info/RECORD
drf_coupons-1.0.dist-info/WHEEL
drf_coupons-1.0.dist-info/metadata.json
drf_coupons-1.0.dist-info/top_level.txt
